buatool/__init__.py
buatool/index.py
buatool/main.py
buatool/util.py
buatool-0.1.1.dist-info/DESCRIPTION.rst
buatool-0.1.1.dist-info/METADATA
buatool-0.1.1.dist-info/RECORD
buatool-0.1.1.dist-info/WHEEL
buatool-0.1.1.dist-info/entry_points.txt
buatool-0.1.1.dist-info/metadata.json
buatool-0.1.1.dist-info/top_level.txt
